sion/__init__.py
sion/sion.py
surface_ion-1.0.6.dist-info/LICENSE
surface_ion-1.0.6.dist-info/METADATA
surface_ion-1.0.6.dist-info/WHEEL
surface_ion-1.0.6.dist-info/top_level.txt
surface_ion-1.0.6.dist-info/RECORD
