Metadata-Version: 2.1
Name: surface-ion
Version: 1.0.6
Summary: Python package for simulation and analysis of ion crystals in surface traps.
Home-page: https://github.com/underforestaaa/Sion
Author: Artem Podlesnyy
Author-email: a.podlesnyy@rqc.ru
License: MIT license
Keywords: surface trap,ion,quantum computing,ion simulation,normal modes,mathieu modes,ion shuttling,voltage optimization
Classifier: Development Status :: 2 - Pre-Alpha
Classifier: Intended Audience :: Developers
Classifier: License :: OSI Approved :: MIT License
Classifier: Natural Language :: English
Classifier: Programming Language :: Python :: 3.6
License-File: LICENSE
Requires-Dist: numpy>=1.13.3
Requires-Dist: cython>=3.0.1
Requires-Dist: jinja2>=2.9.6
Requires-Dist: scipy>=1.12.1
Requires-Dist: scikit-optimize>=0.10.2
Requires-Dist: matplotlib>=3.0.2
Requires-Dist: gdspy>=1.6.13
Requires-Dist: shapely>=2.0.6
Requires-Dist: tqdm>=4.66.6
Requires-Dist: wexpect
